ruff_api-0.2.1.dist-info/METADATA
ruff_api-0.2.1.dist-info/WHEEL
ruff_api-0.2.1.dist-info/licenses/LICENSE
ruff_api/__init__.py
ruff_api/__ruff_version__.py
ruff_api/__version__.py
ruff_api/_rust.pyd
ruff_api/_rust.pyi
ruff_api/errors.py
ruff_api/py.typed
ruff_api/tests/__init__.py
ruff_api/tests/__main__.py
ruff_api/tests/smoke.py
ruff_api-0.2.1.dist-info/RECORD
