Metadata-Version: 2.4
Name: ruff-api
Version: 0.2.1
Classifier: Development Status :: 4 - Beta
Classifier: License :: OSI Approved :: MIT License
Classifier: Programming Language :: Rust
Classifier: Programming Language :: Python :: Implementation :: CPython
Classifier: Programming Language :: Python :: Implementation :: PyPy
Classifier: Programming Language :: Python :: Free Threading :: 2 - Beta
Requires-Dist: attribution==1.8.0 ; extra == 'dev'
Requires-Dist: flake8==7.3.0 ; extra == 'dev'
Requires-Dist: maturin==1.10.2 ; extra == 'dev'
Requires-Dist: mypy==1.19.0 ; extra == 'dev'
Requires-Dist: pytest==8.4.2 ; extra == 'dev'
Requires-Dist: ufmt==2.8.0 ; extra == 'dev'
Requires-Dist: usort==1.0.8.post1 ; extra == 'dev'
Provides-Extra: dev
License-File: LICENSE
Summary: Experimental API for Ruff
Author-email: Amethyst Reese <amethyst@n7.gg>
License-Expression: MIT
Requires-Python: >=3.9
Project-URL: Home, https://github.com/amyreese/ruff-api
